src/__init__.py
src/sample.py
hello_demo_bubble-1.0.0.dist-info/METADATA
hello_demo_bubble-1.0.0.dist-info/WHEEL
hello_demo_bubble-1.0.0.dist-info/top_level.txt
hello_demo_bubble-1.0.0.dist-info/RECORD
