Metadata-Version: 2.1
Name: hello-demo-bubble
Version: 1.0.0
Summary: this is first test app
Home-page: http://some_url.com
Author: something
Author-email: sldjfsldkfl@sina.com
License: UNKNOWN
Platform: UNKNOWN
